odoo8_addon_sentry-8.0.1.0.0.99.dev2-py2.7-nspkg.pth
odoo8_addon_sentry-8.0.1.0.0.99.dev2.dist-info/DESCRIPTION.rst
odoo8_addon_sentry-8.0.1.0.0.99.dev2.dist-info/METADATA
odoo8_addon_sentry-8.0.1.0.0.99.dev2.dist-info/RECORD
odoo8_addon_sentry-8.0.1.0.0.99.dev2.dist-info/WHEEL
odoo8_addon_sentry-8.0.1.0.0.99.dev2.dist-info/metadata.json
odoo8_addon_sentry-8.0.1.0.0.99.dev2.dist-info/namespace_packages.txt
odoo8_addon_sentry-8.0.1.0.0.99.dev2.dist-info/top_level.txt
odoo_addons/sentry/README.rst
odoo_addons/sentry/__init__.py
odoo_addons/sentry/__openerp__.py
odoo_addons/sentry/const.py
odoo_addons/sentry/logutils.py
odoo_addons/sentry/i18n/sentry.pot
odoo_addons/sentry/static/description/icon.png
odoo_addons/sentry/tests/__init__.py
odoo_addons/sentry/tests/test_client.py
odoo_addons/sentry/tests/test_logutils.py
